pyoverseerr.py
pyoverseerr-0.1.40.dist-info/LICENSE
pyoverseerr-0.1.40.dist-info/METADATA
pyoverseerr-0.1.40.dist-info/WHEEL
pyoverseerr-0.1.40.dist-info/top_level.txt
pyoverseerr-0.1.40.dist-info/RECORD
