Metadata-Version: 2.1
Name: pyoverseerr
Version: 0.1.40
Summary: A python module to retrieve information from Overseerr.
Home-page: https://github.com/vaparr/pyoverseerr
Author: Vaparr
Author-email: Vaparr@vaparr.org
License: UNKNOWN
Platform: UNKNOWN
Classifier: Programming Language :: Python :: 3
Classifier: Programming Language :: Python :: 3.7
Classifier: License :: OSI Approved :: MIT License
Classifier: Operating System :: OS Independent
License-File: LICENSE
Requires-Dist: requests
